uun_livecam/__init__.py
uun_livecam/camera.py
uun_livecam/onvif_soap.py
uun_livecam/data/sample-config.json
uun_livecam/data/start.sh
uun_livecam/data/systemd.service
uun_livecam/data/camera-manual/__init__.py
uun_livecam/data/camera-manual/get-info.py
uun_livecam/data/camera-manual/main.py
uun_livecam/data/camera-manual/positions.json
uun_livecam/data/camera-manual/ptz-continuous.py
uun_livecam/data/camera-manual/ptz.py
uun_livecam/data/camera-manual/snapshot.py
uun_livecam/data/camera-manual/wsdl/accesscontrol.wsdl
uun_livecam/data/camera-manual/wsdl/actionengine.wsdl
uun_livecam/data/camera-manual/wsdl/addressing
uun_livecam/data/camera-manual/wsdl/advancedsecurity.wsdl
uun_livecam/data/camera-manual/wsdl/analytics.wsdl
uun_livecam/data/camera-manual/wsdl/analyticsdevice.wsdl
uun_livecam/data/camera-manual/wsdl/b-2.xsd
uun_livecam/data/camera-manual/wsdl/bf-2.xsd
uun_livecam/data/camera-manual/wsdl/bw-2.wsdl
uun_livecam/data/camera-manual/wsdl/deviceio.wsdl
uun_livecam/data/camera-manual/wsdl/devicemgmt.wsdl
uun_livecam/data/camera-manual/wsdl/display.wsdl
uun_livecam/data/camera-manual/wsdl/doorcontrol.wsdl
uun_livecam/data/camera-manual/wsdl/envelope
uun_livecam/data/camera-manual/wsdl/events.wsdl
uun_livecam/data/camera-manual/wsdl/imaging.wsdl
uun_livecam/data/camera-manual/wsdl/include
uun_livecam/data/camera-manual/wsdl/media.wsdl
uun_livecam/data/camera-manual/wsdl/onvif.xsd
uun_livecam/data/camera-manual/wsdl/ptz.wsdl
uun_livecam/data/camera-manual/wsdl/r-2.xsd
uun_livecam/data/camera-manual/wsdl/receiver.wsdl
uun_livecam/data/camera-manual/wsdl/recording.wsdl
uun_livecam/data/camera-manual/wsdl/remotediscovery.wsdl
uun_livecam/data/camera-manual/wsdl/replay.wsdl
uun_livecam/data/camera-manual/wsdl/rw-2.wsdl
uun_livecam/data/camera-manual/wsdl/search.wsdl
uun_livecam/data/camera-manual/wsdl/t-1.xsd
uun_livecam/data/camera-manual/wsdl/types.xsd
uun_livecam/data/camera-manual/wsdl/ws-addr.xsd
uun_livecam/data/camera-manual/wsdl/ws-discovery.xsd
uun_livecam-0.6.0.dist-info/LICENSE.md
uun_livecam-0.6.0.dist-info/METADATA
uun_livecam-0.6.0.dist-info/WHEEL
uun_livecam-0.6.0.dist-info/top_level.txt
uun_livecam-0.6.0.dist-info/RECORD
